{"name":"Inicio de sesión exitoso","id":"inicio-de-sesión-de-usuario;inicio-de-sesión-exitoso","testSteps":[{"number":1,"description":"Dado que \"Laura\" con email \"usuario2@example.com\" y contrasena \"123\"","duration":125,"startTime":"2024-04-09T22:32:23.945125700-05:00[America/Bogota]","result":"SUCCESS","precondition":false,"level":0},{"number":2,"description":"Cuando se realiza una solicitud POST a \"/sesion\" con el email y contrasena validos","duration":7456,"startTime":"2024-04-09T22:32:24.103826300-05:00[America/Bogota]","result":"SUCCESS","precondition":false,"level":0,"children":[{"number":3,"description":"Laura executes a POST on the resource /sesion","duration":6399,"startTime":"2024-04-09T22:32:25.129566500-05:00[America/Bogota]","result":"SUCCESS","precondition":false,"level":1,"children":[{"number":4,"description":"POST http://localhost:3000/sesion","duration":1,"startTime":"2024-04-09T22:32:31.527573600-05:00[America/Bogota]","result":"SUCCESS","restQuery":{"method":"POST","path":"http://localhost:3000/sesion","content":"{\n    \"email\": \"usuario2@example.com\",\n    \"contrasena\": \"123\"\n}","contentType":"application/json","requestHeaders":"Accept\u003d*/*\r\n\t\t\t\tContent-Type\u003dapplication/json","requestCookies":"","responseHeaders":"X-Powered-By: Express\r\nContent-Type: application/json; charset\u003dutf-8\r\nContent-Length: 192\r\nETag: W/\"c0-Ldi7L53fgyrDNw2c1oz7E9oIWSk\"\r\nDate: Wed, 10 Apr 2024 03:32:31 GMT\r\nConnection: keep-alive\r\nKeep-Alive: timeout\u003d5\r","responseCookies":"\r","responseBody":"{\n    \"message\": \"Inicio de sesion exitoso\",\n    \"token\": \"eyJhbGciOiJIUzI1NiIsInR5cCI6IkpXVCJ9.eyJ1c2VySWQiOjQsImlhdCI6MTcxMjcxOTk1MSwiZXhwIjoxNzEyNzIzNTUxfQ.Zr7f6X_Cye3MRkQaSAzy742HPDRRAoWlYzermhZcEmk\"\n}","statusCode":200},"precondition":false,"level":2}]}]},{"number":5,"description":"Entonces la respuesta debe tener un codigo de estado 200","duration":294,"startTime":"2024-04-09T22:32:31.562382400-05:00[America/Bogota]","result":"SUCCESS","precondition":false,"level":0,"children":[{"number":6,"description":"el estatus es 200","duration":58,"startTime":"2024-04-09T22:32:31.778718300-05:00[America/Bogota]","result":"SUCCESS","precondition":false,"level":1}]},{"number":7,"description":"Y la respuesta debe incluir el mensaje \"Inicio de sesion exitoso\"","duration":80,"startTime":"2024-04-09T22:32:31.859470200-05:00[America/Bogota]","result":"SUCCESS","precondition":false,"level":0,"children":[{"number":8,"description":"Verifica el mensaje en la respuesta","duration":45,"startTime":"2024-04-09T22:32:31.872484400-05:00[America/Bogota]","result":"SUCCESS","precondition":false,"level":1}]},{"number":9,"description":"Y la respuesta debe incluir el token","duration":50,"startTime":"2024-04-09T22:32:31.943089200-05:00[America/Bogota]","result":"SUCCESS","precondition":false,"level":0,"children":[{"number":10,"description":"Verifica el token en la respuesta","duration":21,"startTime":"2024-04-09T22:32:31.955771500-05:00[America/Bogota]","result":"SUCCESS","precondition":false,"level":1}]}],"userStory":{"id":"inicio-de-sesión-de-usuario","storyName":"Inicio de sesión de usuario","displayName":"Inicio de sesión de usuario","path":"iniciarSesion.feature","type":"feature","qualifiedTag":{"name":"Inicio de sesión de usuario","type":"feature","displayName":"Inicio de sesión de usuario"}},"featureTag":{"name":"Inicio de sesión de usuario","type":"feature","displayName":"Inicio de sesión de usuario"},"title":"Inicio de sesión exitoso","description":"","tags":[{"name":"Inicio de sesión de usuario","type":"feature","displayName":"Inicio de sesión de usuario"}],"allTags":[{"name":"Inicio de sesión de usuario","type":"feature","displayName":"Inicio de sesión de usuario"}],"startTime":"2024-04-09T22:32:23.481583900-05:00[America/Bogota]","duration":8517,"projectKey":"","isManualTestingUpToDate":false,"manual":false,"testSource":"Cucumber","actors":[{"name":"Laura","can":["call an API at http://localhost:3000"]}],"result":"SUCCESS"}